challonge/__init__.py
challonge/attachment.py
challonge/enums.py
challonge/helpers.py
challonge/match.py
challonge/participant.py
challonge/tournament.py
challonge/user.py
achallonge-1.9.0.dist-info/LICENSE
achallonge-1.9.0.dist-info/METADATA
achallonge-1.9.0.dist-info/WHEEL
achallonge-1.9.0.dist-info/top_level.txt
achallonge-1.9.0.dist-info/RECORD
