Metadata-Version: 2.1
Name: achallonge
Version: 1.9.0
Summary: A python library to use the Challonge API
Home-page: https://github.com/fp12/achallonge
Author: Fabien Poupineau (fp12)
License: MIT
Keywords: challonge,tournament,match
Platform: UNKNOWN
Classifier: Development Status :: 5 - Production/Stable
Classifier: License :: OSI Approved :: MIT License
Classifier: Intended Audience :: Developers
Classifier: Natural Language :: English
Classifier: Operating System :: OS Independent
Classifier: Programming Language :: Python :: 3.5
Classifier: Programming Language :: Python :: 3.6
Classifier: Topic :: Internet
Classifier: Topic :: Software Development :: Libraries
Classifier: Topic :: Software Development :: Libraries :: Python Modules
Classifier: Topic :: Utilities
Requires-Dist: aiohttp (==3.6.0)
Provides-Extra: speed
Requires-Dist: cchardet ; extra == 'speed'
Requires-Dist: aiodns ; extra == 'speed'
